chaosoci/__init__.py
chaosoci/types.py
chaosoci/core/compute/__init__.py
chaosoci/core/compute/actions.py
chaosoci/core/compute/common.py
chaosoci/core/compute/probes.py
chaosoci/core/networking/__init__.py
chaosoci/core/networking/actions.py
chaosoci/core/networking/common.py
chaosoci/core/networking/filters.py
chaosoci/core/networking/probes.py
chaosoci/core/networking/rollbacks.py
chaostoolkit_oci-0.2.0.dist-info/LICENSE
chaostoolkit_oci-0.2.0.dist-info/METADATA
chaostoolkit_oci-0.2.0.dist-info/WHEEL
chaostoolkit_oci-0.2.0.dist-info/top_level.txt
chaostoolkit_oci-0.2.0.dist-info/RECORD
