Metadata-Version: 2.1
Name: chaostoolkit-oci
Version: 0.2.0
Summary: Chaos Toolkit Extension for OCI
Home-page: http://chaostoolkit.org
Author: chaostoolkit Team
Author-email: contact@chaostoolkit.org
License: Apache License Version 2.0
Platform: UNKNOWN
Classifier: Development Status :: 2 - Pre-Alpha
Classifier: Intended Audience :: Developers
Classifier: License :: Freely Distributable
Classifier: Operating System :: OS Independent
Classifier: License :: OSI Approved :: Apache Software License
Classifier: Programming Language :: Python
Classifier: Programming Language :: Python :: 3
Classifier: Programming Language :: Python :: 3.5
Classifier: Programming Language :: Python :: 3.6
Classifier: Programming Language :: Python :: Implementation
Classifier: Programming Language :: Python :: Implementation :: CPython
Requires-Python: >=3.5.*
Requires-Dist: oci (>=2.16)
Requires-Dist: chaostoolkit (>=1.4)
Requires-Dist: chaostoolkit-lib (>=1.10)
